
[
    {
        "account_number": 100,
        "balance": 3500,
        "account_changes":[{"change_number":1}]
    },
    {
        "account_number": 101,
        "balance": 3000,
        "account_changes":[{"change_number":1}]
    },
    {
        "account_number": 102,
        "balance": 4000,
        "account_changes":[{"change_number":2}]
    },
    {
        "account_number": 103,
        "balance": 5000,
        "account_changes":[{"change_number":2}]
    },
    {
        "account_number": 104,
        "balance": 8000,
        "account_changes":[]
    }
]
